arm7/ALU/verilog/alu.v
module alu (
  input [31:0] a, b,
  input [3:0] opcode,
  output reg [31:0] out
);

  // Arithmetic operations
  always @* begin
    case (opcode)
      4'b0000: out = a + b; // ADD
      4'b0001: out = a - b; // SUBTRACT
      4'b0110: out = a + b; // ADD WITH CARRY
      4'b0111: out = a - b; // SUBTRACT WITH BORROW
      default: out = 32'h0; // Invalid opcode
    endcase
  end

  // Logical operations
  always @* begin
    case (opcode)
      4'b0010: out = a & b; // AND
      4'b0011: out = a | b; // OR
      4'b0100: out = a ^ b; // XOR
      4'b1000: out = a << b; // LEFT SHIFT
      4'b1001: out = a >> b; // RIGHT SHIFT
      4'b1010: out = $unsigned(a) >>> b; // UNSIGNED RIGHT SHIFT
      4'b1011: out = ~a; // NOT
      default: out = 32'h0; // Invalid opcode
    endcase
  end

endmodule

arm7/ALU/verilog/alu_tb.v
module alu_tb;

  // Inputs
  reg [31:0] a, b;
  reg [3:0] opcode;

  // Outputs
  wire [31:0] out;

  // Instantiate the module to be tested
  alu dut(
    .a(a),
    .b(b),
    .opcode(opcode),
    .out(out)
  );

  // Clock
  reg clk = 0;
  always #5 clk = ~clk;

  // Test stimulus
  initial begin
	  $dumpfile("alu.vcd");
	  $dumpvars(0, alu_tb);
    // Test ADD
    a = 32'h00000001;
    b = 32'h00000002;
    opcode = 4'b0000;
    #10;
    $display("ADD %h + %h = %h", a, b, out);
    if(out == 32'h00000003);

    // Test SUBTRACT
    a = 32'h00000003;
    b = 32'h00000002;
    opcode = 4'b0001;
    #10;
    $display("SUBTRACT %h - %h = %h", a, b, out);
    if(out == 32'h00000001);

    // Test AND
    a = 32'h55555555;
    b = 32'hAAAAAAAA;
    opcode = 4'b0010;
    #10;
    $display("AND %h & %h = %h", a, b, out);
    if(out == 32'h00000000);

    // Test OR
    a = 32'h55555555;
    b = 32'hAAAAAAAA;
    opcode = 4'b0011;
    #10;
    $display("OR %h | %h = %h", a, b, out);
    if(out == 32'hFFFFFFFF);

    // Test XOR
    a = 32'h55555555;
    b = 32'hAAAAAAAA;
    opcode = 4'b0100;
    #10;
    $display("XOR %h ^ %h = %h", a, b, out);
    if(out == 32'hAAAAAAAA);

    // Test LEFT SHIFT
    a = 32'h00000001;
    b = 5;
    opcode = 4'b1000;
    #10;
    $display("LEFT SHIFT %h << %d = %h", a, b, out);
    if(out == 32'h00000020);

    // Test RIGHT SHIFT
    a = 32'h00000020;
    b = 5;
    opcode = 4'b1001;
    #10;
    $display("RIGHT SHIFT %h >> %d = %h", a, b, out);
    if(out == 32'h00000004);

    // Test UNSIGNED RIGHT SHIFT
    a = 32'h80000000;
    b = 5;
    opcode = 4'b1010;
    #10;
    $display("UNSIGNED RIGHT SHIFT %h >>> %d = %h", a, b, out);
    if(out == 32'h00000010);

    // Test NOT
    a = 32'h00000001;
    opcode = 4'b1011;
    #10;
    $display("NOT ~%h = %h", a, out);
    if(out == 32'hFFFFFFFE);

    $finish;
  end

endmodule

arm7/ALU/verilog/alu.vcd
$date
	Sat Apr  1 15:49:12 2023
$end
$version
	Icarus Verilog
$end
$timescale
	1s
$end
$scope module alu_tb $end
$var wire 32 ! out [31:0] $end
$var reg 32 " a [31:0] $end
$var reg 32 # b [31:0] $end
$var reg 1 $ clk $end
$var reg 4 % opcode [3:0] $end
$scope module dut $end
$var wire 32 & a [31:0] $end
$var wire 32 ' b [31:0] $end
$var wire 4 ( opcode [3:0] $end
$var reg 32 ) out [31:0] $end
$upscope $end
$upscope $end
$enddefinitions $end
#0
$dumpvars
b0 )
b0 (
b10 '
b1 &
b0 %
0$
b10 #
b1 "
b0 !
$end
#5
1$
#10
b1 !
b1 )
0$
b1 %
b1 (
b11 "
b11 &
#15
1$
#20
b0 !
b0 )
0$
b10 %
b10 (
b10101010101010101010101010101010 #
b10101010101010101010101010101010 '
b1010101010101010101010101010101 "
b1010101010101010101010101010101 &
#25
1$
#30
b0 !
b0 )
0$
b11 %
b11 (
#35
1$
#40
b11111111111111111111111111111111 !
b11111111111111111111111111111111 )
0$
b100 %
b100 (
#45
1$
#50
b0 !
b0 )
0$
b1000 %
b1000 (
b101 #
b101 '
b1 "
b1 &
#55
1$
#60
b1 !
b1 )
0$
b1001 %
b1001 (
b100000 "
b100000 &
#65
1$
#70
b0 !
b0 )
0$
b1010 %
b1010 (
b10000000000000000000000000000000 "
b10000000000000000000000000000000 &
#75
1$
#80
b11111111111111111111111111111110 !
b11111111111111111111111111111110 )
0$
b1011 %
b1011 (
b1 "
b1 &
